edenai/__init__.py
edenai/core.py
edenai/workflow.py
edenai_sdk/__init__.py
edenai_sdk/workflow.py
sdk/__init__.py
sdk/main.py
sdk/workflow.py
sdk/sdk/__init__.py
sdk/sdk/main.py
sdk/sdk/workflow.py
tests/__init__.py
tests/example_workflow.py
tests/hoi.py
tests/main.py
tests/test_integration.py
edenai_sdk-0.1.0a4.dist-info/METADATA
edenai_sdk-0.1.0a4.dist-info/WHEEL
edenai_sdk-0.1.0a4.dist-info/top_level.txt
edenai_sdk-0.1.0a4.dist-info/RECORD
