Metadata-Version: 2.1
Name: edenai-sdk
Version: 0.1.0a4
Summary: EdenAI SDK for python
Home-page: https://github.com/edenai/python_sdk
Author: Eden AI
Author-email: contact@edenai.co
Classifier: Programming Language :: Python :: 3
Classifier: License :: OSI Approved :: MIT License
Classifier: Operating System :: OS Independent
Requires-Python: >=3.8
Requires-Dist: certifi==2024.8.30
Requires-Dist: charset-normalizer==3.4.0
Requires-Dist: idna==3.10
Requires-Dist: requests==2.32.3
Requires-Dist: urllib3==2.2.3
